<?xml version='1.0' encoding='UTF-8'?>
<GateDocument version="3">
<!-- The document's features-->

<GateDocumentFeatures>
<Feature>
  <Name className="java.lang.String">Original_document_content_on_load</Name>
  <Value className="java.lang.String"><![CDATA[From: russotto@eng.umd.edu (Matthew T. Russotto)
Date: 22 Apr 1993 03:14:51 GMT
Organization: Project GLUE, University of Maryland, College Park
Lines: 20
Message-ID: <1r52jbINN91b@mojo.eng.umd.edu>
References: <C5uD1u.3oy@apollo.hp.com> <C5uoC0.9I5@noose.ecn.purdue.edu>
NNTP-Posting-Host: tea.eng.umd.edu

In article <C5uoC0.9I5@noose.ecn.purdue.edu> tbrent@bank.ecn.purdue.edu (Timothy J Brent) writes:
>In article <C5uD1u.3oy@apollo.hp.com> goykhman@apollo.hp.com (Red Herring) writes:
>>    Where did you get this information?  The FBI stated they were not
>>   aware of any mass suicide plans, ditto Koresh's attorneys who appeared
>>   on Larry King's Live yesterday, and the survivors claim the fire was started
>>   from the outside...
>
>Actually, ONE of the survivors say it was started by the FBI (tank knocked over lamp).  Another said the Davidians set the fire themselves.

The FBI says that one survivor says they set the fire themselves.

Given that the claim is that the fire was started in 3 places at once,
and that the building was being rammed by a tank and filled with tear
gas, just how did the Davidians manage to co-ordinate such a thing?

-- 
Matthew T. Russotto	russotto@eng.umd.edu	russotto@wam.umd.edu
Some news readers expect "Disclaimer:" here.
Just say NO to police searches and seizures.  Make them use force.
(not responsible for bodily harm resulting from following above advice)
]]></Value>
</Feature>
<Feature>
  <Name className="java.lang.String">gate.SourceURL</Name>
  <Value className="java.lang.String">file:/C:/Users/jian/Documents/NetBeansProjects/NoiseReductionTechniques/mideastPoliticsMix/negative421</Value>
</Feature>
</GateDocumentFeatures>
<!-- The document content area with serialized nodes -->

<TextWithNodes><Node id="0"/>From<Node id="4"/>:<Node id="5"/> <Node id="6"/>russotto<Node id="14"/>@<Node id="15"/>eng<Node id="18"/>.<Node id="19"/>umd<Node id="22"/>.<Node id="23"/>edu<Node id="26"/> <Node id="27"/>(<Node id="28"/>Matthew<Node id="35"/> <Node id="36"/>T<Node id="37"/>.<Node id="38"/> <Node id="39"/>Russotto<Node id="47"/>)<Node id="48"/>
<Node id="49"/>Date<Node id="53"/>:<Node id="54"/> <Node id="55"/>22<Node id="57"/> <Node id="58"/>Apr<Node id="61"/> <Node id="62"/>1993<Node id="66"/> <Node id="67"/>03<Node id="69"/>:<Node id="70"/>14<Node id="72"/>:<Node id="73"/>51<Node id="75"/> <Node id="76"/>GMT<Node id="79"/>
<Node id="80"/>Organization<Node id="92"/>:<Node id="93"/> <Node id="94"/>Project<Node id="101"/> <Node id="102"/>GLUE<Node id="106"/>,<Node id="107"/> <Node id="108"/>University<Node id="118"/> <Node id="119"/>of<Node id="121"/> <Node id="122"/>Maryland<Node id="130"/>,<Node id="131"/> <Node id="132"/>College<Node id="139"/> <Node id="140"/>Park<Node id="144"/>
<Node id="145"/>Lines<Node id="150"/>:<Node id="151"/> <Node id="152"/>20<Node id="154"/>
<Node id="155"/>Message-<Node id="163"/>ID<Node id="165"/>:<Node id="166"/> <Node id="167"/>&lt;<Node id="168"/>1<Node id="169"/>r<Node id="170"/>52<Node id="172"/>jbINN<Node id="177"/>91<Node id="179"/>b<Node id="180"/>@<Node id="181"/>mojo<Node id="185"/>.<Node id="186"/>eng<Node id="189"/>.<Node id="190"/>umd<Node id="193"/>.<Node id="194"/>edu<Node id="197"/>&gt;<Node id="198"/>
<Node id="199"/>References<Node id="209"/>:<Node id="210"/> <Node id="211"/>&lt;<Node id="212"/>C<Node id="213"/>5<Node id="214"/>uD<Node id="216"/>1<Node id="217"/>u<Node id="218"/>.<Node id="219"/>3<Node id="220"/>oy<Node id="222"/>@<Node id="223"/>apollo<Node id="229"/>.<Node id="230"/>hp<Node id="232"/>.<Node id="233"/>com<Node id="236"/>&gt;<Node id="237"/> <Node id="238"/>&lt;<Node id="239"/>C<Node id="240"/>5<Node id="241"/>uoC<Node id="244"/>0<Node id="245"/>.<Node id="246"/>9<Node id="247"/>I<Node id="248"/>5<Node id="249"/>@<Node id="250"/>noose<Node id="255"/>.<Node id="256"/>ecn<Node id="259"/>.<Node id="260"/>purdue<Node id="266"/>.<Node id="267"/>edu<Node id="270"/>&gt;<Node id="271"/>
<Node id="272"/>NNTP-Posting-Host<Node id="289"/>:<Node id="290"/> <Node id="291"/>tea<Node id="294"/>.<Node id="295"/>eng<Node id="298"/>.<Node id="299"/>umd<Node id="302"/>.<Node id="303"/>edu<Node id="306"/>
<Node id="307"/>
<Node id="308"/>In<Node id="310"/> <Node id="311"/>article<Node id="318"/> <Node id="319"/>&lt;<Node id="320"/>C<Node id="321"/>5<Node id="322"/>uoC<Node id="325"/>0<Node id="326"/>.<Node id="327"/>9<Node id="328"/>I<Node id="329"/>5<Node id="330"/>@<Node id="331"/>noose<Node id="336"/>.<Node id="337"/>ecn<Node id="340"/>.<Node id="341"/>purdue<Node id="347"/>.<Node id="348"/>edu<Node id="351"/>&gt;<Node id="352"/> <Node id="353"/>tbrent<Node id="359"/>@<Node id="360"/>bank<Node id="364"/>.<Node id="365"/>ecn<Node id="368"/>.<Node id="369"/>purdue<Node id="375"/>.<Node id="376"/>edu<Node id="379"/> <Node id="380"/>(<Node id="381"/>Timothy<Node id="388"/> <Node id="389"/>J<Node id="390"/> <Node id="391"/>Brent<Node id="396"/>)<Node id="397"/> <Node id="398"/>writes<Node id="404"/>:<Node id="405"/>
<Node id="406"/>&gt;<Node id="407"/>In<Node id="409"/> <Node id="410"/>article<Node id="417"/> <Node id="418"/>&lt;<Node id="419"/>C<Node id="420"/>5<Node id="421"/>uD<Node id="423"/>1<Node id="424"/>u<Node id="425"/>.<Node id="426"/>3<Node id="427"/>oy<Node id="429"/>@<Node id="430"/>apollo<Node id="436"/>.<Node id="437"/>hp<Node id="439"/>.<Node id="440"/>com<Node id="443"/>&gt;<Node id="444"/> <Node id="445"/>goykhman<Node id="453"/>@<Node id="454"/>apollo<Node id="460"/>.<Node id="461"/>hp<Node id="463"/>.<Node id="464"/>com<Node id="467"/> <Node id="468"/>(<Node id="469"/>Red<Node id="472"/> <Node id="473"/>Herring<Node id="480"/>)<Node id="481"/> <Node id="482"/>writes<Node id="488"/>:<Node id="489"/>
<Node id="490"/>&gt;<Node id="491"/>&gt;<Node id="492"/> <Node id="493"/> <Node id="494"/> <Node id="495"/> <Node id="496"/>Where<Node id="501"/> <Node id="502"/>did<Node id="505"/> <Node id="506"/>you<Node id="509"/> <Node id="510"/>get<Node id="513"/> <Node id="514"/>this<Node id="518"/> <Node id="519"/>information<Node id="530"/>?<Node id="531"/> <Node id="532"/> <Node id="533"/>The<Node id="536"/> <Node id="537"/>FBI<Node id="540"/> <Node id="541"/>stated<Node id="547"/> <Node id="548"/>they<Node id="552"/> <Node id="553"/>were<Node id="557"/> <Node id="558"/>not<Node id="561"/>
<Node id="562"/>&gt;<Node id="563"/>&gt;<Node id="564"/> <Node id="565"/> <Node id="566"/> <Node id="567"/>aware<Node id="572"/> <Node id="573"/>of<Node id="575"/> <Node id="576"/>any<Node id="579"/> <Node id="580"/>mass<Node id="584"/> <Node id="585"/>suicide<Node id="592"/> <Node id="593"/>plans<Node id="598"/>,<Node id="599"/> <Node id="600"/>ditto<Node id="605"/> <Node id="606"/>Koresh<Node id="612"/>'s<Node id="614"/> <Node id="615"/>attorneys<Node id="624"/> <Node id="625"/>who<Node id="628"/> <Node id="629"/>appeared<Node id="637"/>
<Node id="638"/>&gt;<Node id="639"/>&gt;<Node id="640"/> <Node id="641"/> <Node id="642"/> <Node id="643"/>on<Node id="645"/> <Node id="646"/>Larry<Node id="651"/> <Node id="652"/>King<Node id="656"/>'s<Node id="658"/> <Node id="659"/>Live<Node id="663"/> <Node id="664"/>yesterday<Node id="673"/>,<Node id="674"/> <Node id="675"/>and<Node id="678"/> <Node id="679"/>the<Node id="682"/> <Node id="683"/>survivors<Node id="692"/> <Node id="693"/>claim<Node id="698"/> <Node id="699"/>the<Node id="702"/> <Node id="703"/>fire<Node id="707"/> <Node id="708"/>was<Node id="711"/> <Node id="712"/>started<Node id="719"/>
<Node id="720"/>&gt;<Node id="721"/>&gt;<Node id="722"/> <Node id="723"/> <Node id="724"/> <Node id="725"/>from<Node id="729"/> <Node id="730"/>the<Node id="733"/> <Node id="734"/>outside<Node id="741"/>.<Node id="742"/>.<Node id="743"/>.<Node id="744"/>
<Node id="745"/>&gt;<Node id="746"/>
<Node id="747"/>&gt;<Node id="748"/>Actually<Node id="756"/>,<Node id="757"/> <Node id="758"/>ONE<Node id="761"/> <Node id="762"/>of<Node id="764"/> <Node id="765"/>the<Node id="768"/> <Node id="769"/>survivors<Node id="778"/> <Node id="779"/>say<Node id="782"/> <Node id="783"/>it<Node id="785"/> <Node id="786"/>was<Node id="789"/> <Node id="790"/>started<Node id="797"/> <Node id="798"/>by<Node id="800"/> <Node id="801"/>the<Node id="804"/> <Node id="805"/>FBI<Node id="808"/> <Node id="809"/>(<Node id="810"/>tank<Node id="814"/> <Node id="815"/>knocked<Node id="822"/> <Node id="823"/>over<Node id="827"/> <Node id="828"/>lamp<Node id="832"/>)<Node id="833"/>.<Node id="834"/> <Node id="835"/> <Node id="836"/>Another<Node id="843"/> <Node id="844"/>said<Node id="848"/> <Node id="849"/>the<Node id="852"/> <Node id="853"/>Davidians<Node id="862"/> <Node id="863"/>set<Node id="866"/> <Node id="867"/>the<Node id="870"/> <Node id="871"/>fire<Node id="875"/> <Node id="876"/>themselves<Node id="886"/>.<Node id="887"/>
<Node id="888"/>
<Node id="889"/>The<Node id="892"/> <Node id="893"/>FBI<Node id="896"/> <Node id="897"/>says<Node id="901"/> <Node id="902"/>that<Node id="906"/> <Node id="907"/>one<Node id="910"/> <Node id="911"/>survivor<Node id="919"/> <Node id="920"/>says<Node id="924"/> <Node id="925"/>they<Node id="929"/> <Node id="930"/>set<Node id="933"/> <Node id="934"/>the<Node id="937"/> <Node id="938"/>fire<Node id="942"/> <Node id="943"/>themselves<Node id="953"/>.<Node id="954"/>
<Node id="955"/>
<Node id="956"/>Given<Node id="961"/> <Node id="962"/>that<Node id="966"/> <Node id="967"/>the<Node id="970"/> <Node id="971"/>claim<Node id="976"/> <Node id="977"/>is<Node id="979"/> <Node id="980"/>that<Node id="984"/> <Node id="985"/>the<Node id="988"/> <Node id="989"/>fire<Node id="993"/> <Node id="994"/>was<Node id="997"/> <Node id="998"/>started<Node id="1005"/> <Node id="1006"/>in<Node id="1008"/> <Node id="1009"/>3<Node id="1010"/> <Node id="1011"/>places<Node id="1017"/> <Node id="1018"/>at<Node id="1020"/> <Node id="1021"/>once<Node id="1025"/>,<Node id="1026"/>
<Node id="1027"/>and<Node id="1030"/> <Node id="1031"/>that<Node id="1035"/> <Node id="1036"/>the<Node id="1039"/> <Node id="1040"/>building<Node id="1048"/> <Node id="1049"/>was<Node id="1052"/> <Node id="1053"/>being<Node id="1058"/> <Node id="1059"/>rammed<Node id="1065"/> <Node id="1066"/>by<Node id="1068"/> <Node id="1069"/>a<Node id="1070"/> <Node id="1071"/>tank<Node id="1075"/> <Node id="1076"/>and<Node id="1079"/> <Node id="1080"/>filled<Node id="1086"/> <Node id="1087"/>with<Node id="1091"/> <Node id="1092"/>tear<Node id="1096"/>
<Node id="1097"/>gas<Node id="1100"/>,<Node id="1101"/> <Node id="1102"/>just<Node id="1106"/> <Node id="1107"/>how<Node id="1110"/> <Node id="1111"/>did<Node id="1114"/> <Node id="1115"/>the<Node id="1118"/> <Node id="1119"/>Davidians<Node id="1128"/> <Node id="1129"/>manage<Node id="1135"/> <Node id="1136"/>to<Node id="1138"/> <Node id="1139"/>co-ordinate<Node id="1150"/> <Node id="1151"/>such<Node id="1155"/> <Node id="1156"/>a<Node id="1157"/> <Node id="1158"/>thing<Node id="1163"/>?<Node id="1164"/>
<Node id="1165"/>
<Node id="1166"/>-<Node id="1167"/>-<Node id="1168"/> <Node id="1169"/>
<Node id="1170"/>Matthew<Node id="1177"/> <Node id="1178"/>T<Node id="1179"/>.<Node id="1180"/> <Node id="1181"/>Russotto<Node id="1189"/>	<Node id="1190"/>russotto<Node id="1198"/>@<Node id="1199"/>eng<Node id="1202"/>.<Node id="1203"/>umd<Node id="1206"/>.<Node id="1207"/>edu<Node id="1210"/>	<Node id="1211"/>russotto<Node id="1219"/>@<Node id="1220"/>wam<Node id="1223"/>.<Node id="1224"/>umd<Node id="1227"/>.<Node id="1228"/>edu<Node id="1231"/>
<Node id="1232"/>Some<Node id="1236"/> <Node id="1237"/>news<Node id="1241"/> <Node id="1242"/>readers<Node id="1249"/> <Node id="1250"/>expect<Node id="1256"/> <Node id="1257"/>"<Node id="1258"/>Disclaimer<Node id="1268"/>:<Node id="1269"/>"<Node id="1270"/> <Node id="1271"/>here<Node id="1275"/>.<Node id="1276"/>
<Node id="1277"/>Just<Node id="1281"/> <Node id="1282"/>say<Node id="1285"/> <Node id="1286"/>NO<Node id="1288"/> <Node id="1289"/>to<Node id="1291"/> <Node id="1292"/>police<Node id="1298"/> <Node id="1299"/>searches<Node id="1307"/> <Node id="1308"/>and<Node id="1311"/> <Node id="1312"/>seizures<Node id="1320"/>.<Node id="1321"/> <Node id="1322"/> <Node id="1323"/>Make<Node id="1327"/> <Node id="1328"/>them<Node id="1332"/> <Node id="1333"/>use<Node id="1336"/> <Node id="1337"/>force<Node id="1342"/>.<Node id="1343"/>
<Node id="1344"/>(<Node id="1345"/>not<Node id="1348"/> <Node id="1349"/>responsible<Node id="1360"/> <Node id="1361"/>for<Node id="1364"/> <Node id="1365"/>bodily<Node id="1371"/> <Node id="1372"/>harm<Node id="1376"/> <Node id="1377"/>resulting<Node id="1386"/> <Node id="1387"/>from<Node id="1391"/> <Node id="1392"/>following<Node id="1401"/> <Node id="1402"/>above<Node id="1407"/> <Node id="1408"/>advice<Node id="1414"/>)<Node id="1415"/>
<Node id="1416"/></TextWithNodes>
<!-- The default annotation set -->

<AnnotationSet>
<Annotation EndNode="1416" StartNode="0" Type="Mention" Id="9999999">
<Feature>
<Name classname="java.lang.String">Class</Name>
<Value classname="java.lang.String">0</Value>
</Feature>
</Annotation>

<Annotation Id="3" Type="Token" StartNode="6" EndNode="14">
<Feature>
  <Name className="java.lang.String">string</Name>
  <Value className="java.lang.String">russotto</Value>
</Feature>
</Annotation>
<Annotation Id="12" Type="Token" StartNode="28" EndNode="35">
<Feature>
  <Name className="java.lang.String">string</Name>
  <Value className="java.lang.String">Matthew</Value>
</Feature>
</Annotation>
<Annotation Id="17" Type="Token" StartNode="39" EndNode="47">
<Feature>
  <Name className="java.lang.String">string</Name>
  <Value className="java.lang.String">Russotto</Value>
</Feature>
</Annotation>
<Annotation Id="37" Type="Token" StartNode="80" EndNode="92">
<Feature>
  <Name className="java.lang.String">string</Name>
  <Value className="java.lang.String">Organization</Value>
</Feature>
</Annotation>
<Annotation Id="40" Type="Token" StartNode="94" EndNode="101">
<Feature>
  <Name className="java.lang.String">string</Name>
  <Value className="java.lang.String">Project</Value>
</Feature>
</Annotation>
<Annotation Id="45" Type="Token" StartNode="108" EndNode="118">
<Feature>
  <Name className="java.lang.String">string</Name>
  <Value className="java.lang.String">University</Value>
</Feature>
</Annotation>
<Annotation Id="49" Type="Token" StartNode="122" EndNode="130">
<Feature>
  <Name className="java.lang.String">string</Name>
  <Value className="java.lang.String">Maryland</Value>
</Feature>
</Annotation>
<Annotation Id="52" Type="Token" StartNode="132" EndNode="139">
<Feature>
  <Name className="java.lang.String">string</Name>
  <Value className="java.lang.String">College</Value>
</Feature>
</Annotation>
<Annotation Id="61" Type="Token" StartNode="155" EndNode="163">
<Feature>
  <Name className="java.lang.String">string</Name>
  <Value className="java.lang.String">Message-</Value>
</Feature>
</Annotation>
<Annotation Id="82" Type="Token" StartNode="199" EndNode="209">
<Feature>
  <Name className="java.lang.String">string</Name>
  <Value className="java.lang.String">References</Value>
</Feature>
</Annotation>
<Annotation Id="95" Type="Token" StartNode="223" EndNode="229">
<Feature>
  <Name className="java.lang.String">string</Name>
  <Value className="java.lang.String">apollo</Value>
</Feature>
</Annotation>
<Annotation Id="116" Type="Token" StartNode="260" EndNode="266">
<Feature>
  <Name className="java.lang.String">string</Name>
  <Value className="java.lang.String">purdue</Value>
</Feature>
</Annotation>
<Annotation Id="121" Type="Token" StartNode="272" EndNode="289">
<Feature>
  <Name className="java.lang.String">string</Name>
  <Value className="java.lang.String">NNTP-Posting-Host</Value>
</Feature>
</Annotation>
<Annotation Id="135" Type="Token" StartNode="311" EndNode="318">
<Feature>
  <Name className="java.lang.String">string</Name>
  <Value className="java.lang.String">article</Value>
</Feature>
</Annotation>
<Annotation Id="156" Type="Token" StartNode="353" EndNode="359">
<Feature>
  <Name className="java.lang.String">string</Name>
  <Value className="java.lang.String">tbrent</Value>
</Feature>
</Annotation>
<Annotation Id="151" Type="Token" StartNode="341" EndNode="347">
<Feature>
  <Name className="java.lang.String">string</Name>
  <Value className="java.lang.String">purdue</Value>
</Feature>
</Annotation>
<Annotation Id="174" Type="Token" StartNode="398" EndNode="404">
<Feature>
  <Name className="java.lang.String">string</Name>
  <Value className="java.lang.String">writes</Value>
</Feature>
</Annotation>
<Annotation Id="162" Type="Token" StartNode="369" EndNode="375">
<Feature>
  <Name className="java.lang.String">string</Name>
  <Value className="java.lang.String">purdue</Value>
</Feature>
</Annotation>
<Annotation Id="167" Type="Token" StartNode="381" EndNode="388">
<Feature>
  <Name className="java.lang.String">string</Name>
  <Value className="java.lang.String">Timothy</Value>
</Feature>
</Annotation>
<Annotation Id="180" Type="Token" StartNode="410" EndNode="417">
<Feature>
  <Name className="java.lang.String">string</Name>
  <Value className="java.lang.String">article</Value>
</Feature>
</Annotation>
<Annotation Id="201" Type="Token" StartNode="454" EndNode="460">
<Feature>
  <Name className="java.lang.String">string</Name>
  <Value className="java.lang.String">apollo</Value>
</Feature>
</Annotation>
<Annotation Id="199" Type="Token" StartNode="445" EndNode="453">
<Feature>
  <Name className="java.lang.String">string</Name>
  <Value className="java.lang.String">goykhman</Value>
</Feature>
</Annotation>
<Annotation Id="192" Type="Token" StartNode="430" EndNode="436">
<Feature>
  <Name className="java.lang.String">string</Name>
  <Value className="java.lang.String">apollo</Value>
</Feature>
</Annotation>
<Annotation Id="213" Type="Token" StartNode="482" EndNode="488">
<Feature>
  <Name className="java.lang.String">string</Name>
  <Value className="java.lang.String">writes</Value>
</Feature>
</Annotation>
<Annotation Id="210" Type="Token" StartNode="473" EndNode="480">
<Feature>
  <Name className="java.lang.String">string</Name>
  <Value className="java.lang.String">Herring</Value>
</Feature>
</Annotation>
<Annotation Id="232" Type="Token" StartNode="519" EndNode="530">
<Feature>
  <Name className="java.lang.String">string</Name>
  <Value className="java.lang.String">information</Value>
</Feature>
</Annotation>
<Annotation Id="240" Type="Token" StartNode="541" EndNode="547">
<Feature>
  <Name className="java.lang.String">string</Name>
  <Value className="java.lang.String">stated</Value>
</Feature>
</Annotation>
<Annotation Id="272" Type="Token" StartNode="615" EndNode="624">
<Feature>
  <Name className="java.lang.String">string</Name>
  <Value className="java.lang.String">attorneys</Value>
</Feature>
</Annotation>
<Annotation Id="276" Type="Token" StartNode="629" EndNode="637">
<Feature>
  <Name className="java.lang.String">string</Name>
  <Value className="java.lang.String">appeared</Value>
</Feature>
</Annotation>
<Annotation Id="261" Type="Token" StartNode="585" EndNode="592">
<Feature>
  <Name className="java.lang.String">string</Name>
  <Value className="java.lang.String">suicide</Value>
</Feature>
</Annotation>
<Annotation Id="268" Type="Token" StartNode="606" EndNode="612">
<Feature>
  <Name className="java.lang.String">string</Name>
  <Value className="java.lang.String">Koresh</Value>
</Feature>
</Annotation>
<Annotation Id="310" Type="Token" StartNode="712" EndNode="719">
<Feature>
  <Name className="java.lang.String">string</Name>
  <Value className="java.lang.String">started</Value>
</Feature>
</Annotation>
<Annotation Id="293" Type="Token" StartNode="664" EndNode="673">
<Feature>
  <Name className="java.lang.String">string</Name>
  <Value className="java.lang.String">yesterday</Value>
</Feature>
</Annotation>
<Annotation Id="300" Type="Token" StartNode="683" EndNode="692">
<Feature>
  <Name className="java.lang.String">string</Name>
  <Value className="java.lang.String">survivors</Value>
</Feature>
</Annotation>
<Annotation Id="338" Type="Token" StartNode="769" EndNode="778">
<Feature>
  <Name className="java.lang.String">string</Name>
  <Value className="java.lang.String">survivors</Value>
</Feature>
</Annotation>
<Annotation Id="346" Type="Token" StartNode="790" EndNode="797">
<Feature>
  <Name className="java.lang.String">string</Name>
  <Value className="java.lang.String">started</Value>
</Feature>
</Annotation>
<Annotation Id="321" Type="Token" StartNode="734" EndNode="741">
<Feature>
  <Name className="java.lang.String">string</Name>
  <Value className="java.lang.String">outside</Value>
</Feature>
</Annotation>
<Annotation Id="329" Type="Token" StartNode="748" EndNode="756">
<Feature>
  <Name className="java.lang.String">string</Name>
  <Value className="java.lang.String">Actually</Value>
</Feature>
</Annotation>
<Annotation Id="372" Type="Token" StartNode="853" EndNode="862">
<Feature>
  <Name className="java.lang.String">string</Name>
  <Value className="java.lang.String">Davidians</Value>
</Feature>
</Annotation>
<Annotation Id="380" Type="Token" StartNode="876" EndNode="886">
<Feature>
  <Name className="java.lang.String">string</Name>
  <Value className="java.lang.String">themselves</Value>
</Feature>
</Annotation>
<Annotation Id="357" Type="Token" StartNode="815" EndNode="822">
<Feature>
  <Name className="java.lang.String">string</Name>
  <Value className="java.lang.String">knocked</Value>
</Feature>
</Annotation>
<Annotation Id="366" Type="Token" StartNode="836" EndNode="843">
<Feature>
  <Name className="java.lang.String">string</Name>
  <Value className="java.lang.String">Another</Value>
</Feature>
</Annotation>
<Annotation Id="406" Type="Token" StartNode="943" EndNode="953">
<Feature>
  <Name className="java.lang.String">string</Name>
  <Value className="java.lang.String">themselves</Value>
</Feature>
</Annotation>
<Annotation Id="394" Type="Token" StartNode="911" EndNode="919">
<Feature>
  <Name className="java.lang.String">string</Name>
  <Value className="java.lang.String">survivor</Value>
</Feature>
</Annotation>
<Annotation Id="447" Type="Token" StartNode="1040" EndNode="1048">
<Feature>
  <Name className="java.lang.String">string</Name>
  <Value className="java.lang.String">building</Value>
</Feature>
</Annotation>
<Annotation Id="434" Type="Token" StartNode="1011" EndNode="1017">
<Feature>
  <Name className="java.lang.String">string</Name>
  <Value className="java.lang.String">places</Value>
</Feature>
</Annotation>
<Annotation Id="428" Type="Token" StartNode="998" EndNode="1005">
<Feature>
  <Name className="java.lang.String">string</Name>
  <Value className="java.lang.String">started</Value>
</Feature>
</Annotation>
<Annotation Id="463" Type="Token" StartNode="1080" EndNode="1086">
<Feature>
  <Name className="java.lang.String">string</Name>
  <Value className="java.lang.String">filled</Value>
</Feature>
</Annotation>
<Annotation Id="453" Type="Token" StartNode="1059" EndNode="1065">
<Feature>
  <Name className="java.lang.String">string</Name>
  <Value className="java.lang.String">rammed</Value>
</Feature>
</Annotation>
<Annotation Id="505" Type="Token" StartNode="1181" EndNode="1189">
<Feature>
  <Name className="java.lang.String">string</Name>
  <Value className="java.lang.String">Russotto</Value>
</Feature>
</Annotation>
<Annotation Id="507" Type="Token" StartNode="1190" EndNode="1198">
<Feature>
  <Name className="java.lang.String">string</Name>
  <Value className="java.lang.String">russotto</Value>
</Feature>
</Annotation>
<Annotation Id="500" Type="Token" StartNode="1170" EndNode="1177">
<Feature>
  <Name className="java.lang.String">string</Name>
  <Value className="java.lang.String">Matthew</Value>
</Feature>
</Annotation>
<Annotation Id="486" Type="Token" StartNode="1139" EndNode="1150">
<Feature>
  <Name className="java.lang.String">string</Name>
  <Value className="java.lang.String">co-ordinate</Value>
</Feature>
</Annotation>
<Annotation Id="480" Type="Token" StartNode="1119" EndNode="1128">
<Feature>
  <Name className="java.lang.String">string</Name>
  <Value className="java.lang.String">Davidians</Value>
</Feature>
</Annotation>
<Annotation Id="482" Type="Token" StartNode="1129" EndNode="1135">
<Feature>
  <Name className="java.lang.String">string</Name>
  <Value className="java.lang.String">manage</Value>
</Feature>
</Annotation>
<Annotation Id="549" Type="Token" StartNode="1299" EndNode="1307">
<Feature>
  <Name className="java.lang.String">string</Name>
  <Value className="java.lang.String">searches</Value>
</Feature>
</Annotation>
<Annotation Id="547" Type="Token" StartNode="1292" EndNode="1298">
<Feature>
  <Name className="java.lang.String">string</Name>
  <Value className="java.lang.String">police</Value>
</Feature>
</Annotation>
<Annotation Id="553" Type="Token" StartNode="1312" EndNode="1320">
<Feature>
  <Name className="java.lang.String">string</Name>
  <Value className="java.lang.String">seizures</Value>
</Feature>
</Annotation>
<Annotation Id="573" Type="Token" StartNode="1365" EndNode="1371">
<Feature>
  <Name className="java.lang.String">string</Name>
  <Value className="java.lang.String">bodily</Value>
</Feature>
</Annotation>
<Annotation Id="569" Type="Token" StartNode="1349" EndNode="1360">
<Feature>
  <Name className="java.lang.String">string</Name>
  <Value className="java.lang.String">responsible</Value>
</Feature>
</Annotation>
<Annotation Id="515" Type="Token" StartNode="1211" EndNode="1219">
<Feature>
  <Name className="java.lang.String">string</Name>
  <Value className="java.lang.String">russotto</Value>
</Feature>
</Annotation>
<Annotation Id="527" Type="Token" StartNode="1242" EndNode="1249">
<Feature>
  <Name className="java.lang.String">string</Name>
  <Value className="java.lang.String">readers</Value>
</Feature>
</Annotation>
<Annotation Id="532" Type="Token" StartNode="1258" EndNode="1268">
<Feature>
  <Name className="java.lang.String">string</Name>
  <Value className="java.lang.String">Disclaimer</Value>
</Feature>
</Annotation>
<Annotation Id="529" Type="Token" StartNode="1250" EndNode="1256">
<Feature>
  <Name className="java.lang.String">string</Name>
  <Value className="java.lang.String">expect</Value>
</Feature>
</Annotation>
<Annotation Id="577" Type="Token" StartNode="1377" EndNode="1386">
<Feature>
  <Name className="java.lang.String">string</Name>
  <Value className="java.lang.String">resulting</Value>
</Feature>
</Annotation>
<Annotation Id="581" Type="Token" StartNode="1392" EndNode="1401">
<Feature>
  <Name className="java.lang.String">string</Name>
  <Value className="java.lang.String">following</Value>
</Feature>
</Annotation>
<Annotation Id="585" Type="Token" StartNode="1408" EndNode="1414">
<Feature>
  <Name className="java.lang.String">string</Name>
  <Value className="java.lang.String">advice</Value>
</Feature>
</Annotation>
</AnnotationSet>
<AnnotationSet Name="Original markups"> </AnnotationSet>
</GateDocument>