<?xml version='1.0' encoding='UTF-8'?>
<GateDocument version="3">
<!-- The document's features-->

<GateDocumentFeatures>
<Feature>
  <Name className="java.lang.String">Original_document_content_on_load</Name>
  <Value className="java.lang.String">From: francesca_M._Benson@fourd.com
Date: 19 Apr 1993 09:41:43 -0500
Organization: 4th Dimension BBS
Lines: 7
Sender: daemon@cs.utexas.edu
Message-ID: &lt;1993Apr19.032605.235134@fourd.com>
NNTP-Posting-Host: cs.utexas.edu

What an anal retentive you are wimp.

********************************************************************
System: fourd.com                                Phone: 617-494-0565
Cute quote:  Being a computer means never having to say you're sorry
********************************************************************

</Value>
</Feature>
<Feature>
  <Name className="java.lang.String">gate.SourceURL</Name>
  <Value className="java.lang.String">file:/C:/Users/jian/Documents/NetBeansProjects/NoiseReductionTechniques/mideastPoliticsMix/positive1445</Value>
</Feature>
</GateDocumentFeatures>
<!-- The document content area with serialized nodes -->

<TextWithNodes><Node id="0"/>From<Node id="4"/>:<Node id="5"/> <Node id="6"/>francesca<Node id="15"/>_<Node id="16"/>M<Node id="17"/>.<Node id="18"/>_<Node id="19"/>Benson<Node id="25"/>@<Node id="26"/>fourd<Node id="31"/>.<Node id="32"/>com<Node id="35"/>
<Node id="36"/>Date<Node id="40"/>:<Node id="41"/> <Node id="42"/>19<Node id="44"/> <Node id="45"/>Apr<Node id="48"/> <Node id="49"/>1993<Node id="53"/> <Node id="54"/>09<Node id="56"/>:<Node id="57"/>41<Node id="59"/>:<Node id="60"/>43<Node id="62"/> <Node id="63"/>-<Node id="64"/>0500<Node id="68"/>
<Node id="69"/>Organization<Node id="81"/>:<Node id="82"/> <Node id="83"/>4th<Node id="86"/> <Node id="87"/>Dimension<Node id="96"/> <Node id="97"/>BBS<Node id="100"/>
<Node id="101"/>Lines<Node id="106"/>:<Node id="107"/> <Node id="108"/>7<Node id="109"/>
<Node id="110"/>Sender<Node id="116"/>:<Node id="117"/> <Node id="118"/>daemon<Node id="124"/>@<Node id="125"/>cs<Node id="127"/>.<Node id="128"/>utexas<Node id="134"/>.<Node id="135"/>edu<Node id="138"/>
<Node id="139"/>Message-<Node id="147"/>ID<Node id="149"/>:<Node id="150"/> <Node id="151"/>&lt;<Node id="152"/>1993<Node id="156"/>Apr<Node id="159"/>19<Node id="161"/>.<Node id="162"/>032605<Node id="168"/>.<Node id="169"/>235134<Node id="175"/>@<Node id="176"/>fourd<Node id="181"/>.<Node id="182"/>com<Node id="185"/>&gt;<Node id="186"/>
<Node id="187"/>NNTP-Posting-Host<Node id="204"/>:<Node id="205"/> <Node id="206"/>cs<Node id="208"/>.<Node id="209"/>utexas<Node id="215"/>.<Node id="216"/>edu<Node id="219"/>
<Node id="220"/>
<Node id="221"/>What<Node id="225"/> <Node id="226"/>an<Node id="228"/> <Node id="229"/>anal<Node id="233"/> <Node id="234"/>retentive<Node id="243"/> <Node id="244"/>you<Node id="247"/> <Node id="248"/>are<Node id="251"/> <Node id="252"/>wimp<Node id="256"/>.<Node id="257"/>
<Node id="258"/>
<Node id="259"/>*<Node id="260"/>*<Node id="261"/>*<Node id="262"/>*<Node id="263"/>*<Node id="264"/>*<Node id="265"/>*<Node id="266"/>*<Node id="267"/>*<Node id="268"/>*<Node id="269"/>*<Node id="270"/>*<Node id="271"/>*<Node id="272"/>*<Node id="273"/>*<Node id="274"/>*<Node id="275"/>*<Node id="276"/>*<Node id="277"/>*<Node id="278"/>*<Node id="279"/>*<Node id="280"/>*<Node id="281"/>*<Node id="282"/>*<Node id="283"/>*<Node id="284"/>*<Node id="285"/>*<Node id="286"/>*<Node id="287"/>*<Node id="288"/>*<Node id="289"/>*<Node id="290"/>*<Node id="291"/>*<Node id="292"/>*<Node id="293"/>*<Node id="294"/>*<Node id="295"/>*<Node id="296"/>*<Node id="297"/>*<Node id="298"/>*<Node id="299"/>*<Node id="300"/>*<Node id="301"/>*<Node id="302"/>*<Node id="303"/>*<Node id="304"/>*<Node id="305"/>*<Node id="306"/>*<Node id="307"/>*<Node id="308"/>*<Node id="309"/>*<Node id="310"/>*<Node id="311"/>*<Node id="312"/>*<Node id="313"/>*<Node id="314"/>*<Node id="315"/>*<Node id="316"/>*<Node id="317"/>*<Node id="318"/>*<Node id="319"/>*<Node id="320"/>*<Node id="321"/>*<Node id="322"/>*<Node id="323"/>*<Node id="324"/>*<Node id="325"/>*<Node id="326"/>*<Node id="327"/>
<Node id="328"/>System<Node id="334"/>:<Node id="335"/> <Node id="336"/>fourd<Node id="341"/>.<Node id="342"/>com<Node id="345"/> <Node id="346"/> <Node id="347"/> <Node id="348"/> <Node id="349"/> <Node id="350"/> <Node id="351"/> <Node id="352"/> <Node id="353"/> <Node id="354"/> <Node id="355"/> <Node id="356"/> <Node id="357"/> <Node id="358"/> <Node id="359"/> <Node id="360"/> <Node id="361"/> <Node id="362"/> <Node id="363"/> <Node id="364"/> <Node id="365"/> <Node id="366"/> <Node id="367"/> <Node id="368"/> <Node id="369"/> <Node id="370"/> <Node id="371"/> <Node id="372"/> <Node id="373"/> <Node id="374"/> <Node id="375"/> <Node id="376"/> <Node id="377"/>Phone<Node id="382"/>:<Node id="383"/> <Node id="384"/>617<Node id="387"/>-<Node id="388"/>494<Node id="391"/>-<Node id="392"/>0565<Node id="396"/>
<Node id="397"/>Cute<Node id="401"/> <Node id="402"/>quote<Node id="407"/>:<Node id="408"/> <Node id="409"/> <Node id="410"/>Being<Node id="415"/> <Node id="416"/>a<Node id="417"/> <Node id="418"/>computer<Node id="426"/> <Node id="427"/>means<Node id="432"/> <Node id="433"/>never<Node id="438"/> <Node id="439"/>having<Node id="445"/> <Node id="446"/>to<Node id="448"/> <Node id="449"/>say<Node id="452"/> <Node id="453"/>you<Node id="456"/>'re<Node id="459"/> <Node id="460"/>sorry<Node id="465"/>
<Node id="466"/>*<Node id="467"/>*<Node id="468"/>*<Node id="469"/>*<Node id="470"/>*<Node id="471"/>*<Node id="472"/>*<Node id="473"/>*<Node id="474"/>*<Node id="475"/>*<Node id="476"/>*<Node id="477"/>*<Node id="478"/>*<Node id="479"/>*<Node id="480"/>*<Node id="481"/>*<Node id="482"/>*<Node id="483"/>*<Node id="484"/>*<Node id="485"/>*<Node id="486"/>*<Node id="487"/>*<Node id="488"/>*<Node id="489"/>*<Node id="490"/>*<Node id="491"/>*<Node id="492"/>*<Node id="493"/>*<Node id="494"/>*<Node id="495"/>*<Node id="496"/>*<Node id="497"/>*<Node id="498"/>*<Node id="499"/>*<Node id="500"/>*<Node id="501"/>*<Node id="502"/>*<Node id="503"/>*<Node id="504"/>*<Node id="505"/>*<Node id="506"/>*<Node id="507"/>*<Node id="508"/>*<Node id="509"/>*<Node id="510"/>*<Node id="511"/>*<Node id="512"/>*<Node id="513"/>*<Node id="514"/>*<Node id="515"/>*<Node id="516"/>*<Node id="517"/>*<Node id="518"/>*<Node id="519"/>*<Node id="520"/>*<Node id="521"/>*<Node id="522"/>*<Node id="523"/>*<Node id="524"/>*<Node id="525"/>*<Node id="526"/>*<Node id="527"/>*<Node id="528"/>*<Node id="529"/>*<Node id="530"/>*<Node id="531"/>*<Node id="532"/>*<Node id="533"/>*<Node id="534"/>
<Node id="535"/>
<Node id="536"/></TextWithNodes>
<!-- The default annotation set -->

<AnnotationSet>
<Annotation EndNode="536" StartNode="0" Type="Mention" Id="9999999">
<Feature>
<Name classname="java.lang.String">Class</Name>
<Value classname="java.lang.String">1</Value>
</Feature>
</Annotation>

<Annotation Id="3" Type="Token" StartNode="6" EndNode="15">
<Feature>
  <Name className="java.lang.String">string</Name>
  <Value className="java.lang.String">francesca</Value>
</Feature>
</Annotation>
<Annotation Id="8" Type="Token" StartNode="19" EndNode="25">
<Feature>
  <Name className="java.lang.String">string</Name>
  <Value className="java.lang.String">Benson</Value>
</Feature>
</Annotation>
<Annotation Id="32" Type="Token" StartNode="69" EndNode="81">
<Feature>
  <Name className="java.lang.String">string</Name>
  <Value className="java.lang.String">Organization</Value>
</Feature>
</Annotation>
<Annotation Id="38" Type="Token" StartNode="87" EndNode="96">
<Feature>
  <Name className="java.lang.String">string</Name>
  <Value className="java.lang.String">Dimension</Value>
</Feature>
</Annotation>
<Annotation Id="47" Type="Token" StartNode="110" EndNode="116">
<Feature>
  <Name className="java.lang.String">string</Name>
  <Value className="java.lang.String">Sender</Value>
</Feature>
</Annotation>
<Annotation Id="50" Type="Token" StartNode="118" EndNode="124">
<Feature>
  <Name className="java.lang.String">string</Name>
  <Value className="java.lang.String">daemon</Value>
</Feature>
</Annotation>
<Annotation Id="54" Type="Token" StartNode="128" EndNode="134">
<Feature>
  <Name className="java.lang.String">string</Name>
  <Value className="java.lang.String">utexas</Value>
</Feature>
</Annotation>
<Annotation Id="58" Type="Token" StartNode="139" EndNode="147">
<Feature>
  <Name className="java.lang.String">string</Name>
  <Value className="java.lang.String">Message-</Value>
</Feature>
</Annotation>
<Annotation Id="69" Type="Token" StartNode="169" EndNode="175">
</Annotation>
<Annotation Id="67" Type="Token" StartNode="162" EndNode="168">
</Annotation>
<Annotation Id="76" Type="Token" StartNode="187" EndNode="204">
<Feature>
  <Name className="java.lang.String">string</Name>
  <Value className="java.lang.String">NNTP-Posting-Host</Value>
</Feature>
</Annotation>
<Annotation Id="81" Type="Token" StartNode="209" EndNode="215">
<Feature>
  <Name className="java.lang.String">string</Name>
  <Value className="java.lang.String">utexas</Value>
</Feature>
</Annotation>
<Annotation Id="92" Type="Token" StartNode="234" EndNode="243">
<Feature>
  <Name className="java.lang.String">string</Name>
  <Value className="java.lang.String">retentive</Value>
</Feature>
</Annotation>
<Annotation Id="171" Type="Token" StartNode="328" EndNode="334">
<Feature>
  <Name className="java.lang.String">string</Name>
  <Value className="java.lang.String">System</Value>
</Feature>
</Annotation>
<Annotation Id="234" Type="Token" StartNode="439" EndNode="445">
<Feature>
  <Name className="java.lang.String">string</Name>
  <Value className="java.lang.String">having</Value>
</Feature>
</Annotation>
<Annotation Id="228" Type="Token" StartNode="418" EndNode="426">
<Feature>
  <Name className="java.lang.String">string</Name>
  <Value className="java.lang.String">computer</Value>
</Feature>
</Annotation>
</AnnotationSet>
<AnnotationSet Name="Original markups"> </AnnotationSet>
</GateDocument>