<?xml version='1.0' encoding='UTF-8'?>
<GateDocument version="3">
<!-- The document's features-->

<GateDocumentFeatures>
<Feature>
  <Name className="java.lang.String">Original_document_content_on_load</Name>
  <Value className="java.lang.String">From: fcrary@ucsu.Colorado.EDU (Frank Crary)
Message-ID: &lt;1993Apr6.035052.18187@ucsu.Colorado.EDU>
Sender: news@ucsu.Colorado.EDU (USENET News System)
Nntp-Posting-Host: ucsu.colorado.edu
Organization: University of Colorado, Boulder
References: &lt;1993Apr3.075441.20755@osuunx.ucc.okstate.edu> &lt;1pqsruINNiae@hp-col.col.hp.com>
Date: Tue, 6 Apr 1993 03:50:52 GMT
Lines: 29

In article &lt;1pqsruINNiae@hp-col.col.hp.com> dduff@col.hp.com (Dave Duff) writes:
>Does anyone really believe the Swiss have had no war within their borders
>because every adult male owns a rifle? I'm a great admirer of the Swiss, but
>500 years of peace on their turf has zilch to do with gun ownership. Can you
>picture Hitler, with Panzers and Focke-Wulfs poised on the border, losing
>sleep over a few thousand expert rifleman? Sure. 

The Swiss population is (and well was) far larger than that. I think
your question should be, "...losing sleep over a million expert
riflemen?" Certainly he could have conquered Switzerland, but
a million armed militiamen (especially in a mountainous area, 
where tanks' effectiveness is limited) would have made it a
real pain. The question a conqueror would ask, is "is it worth 
the trouble?" The more difficult an invasion is, the more likely
the answer would be "no." Certainly a million riflemen (as
opposed to a professional army of only ten or twenty thousand, the
best a country the size of Switzerland could support), makes
invasions more difficult.

>Hitler stayed out of Switzerland because the Swiss run the money in this
>world.

Really? In 1939? I'm not even sure you could prove that today (despite
the steriotype.) Certainly the Swiss bankers were not essential
to the German war-time economy.

                                           Frank Crary
                                           CU Boulder

</Value>
</Feature>
<Feature>
  <Name className="java.lang.String">gate.SourceURL</Name>
  <Value className="java.lang.String">file:/C:/Users/jian/Documents/NetBeansProjects/NoiseReductionTechniques/mideastPoliticsMix/negative1152</Value>
</Feature>
</GateDocumentFeatures>
<!-- The document content area with serialized nodes -->

<TextWithNodes><Node id="0"/>From<Node id="4"/>:<Node id="5"/> <Node id="6"/>fcrary<Node id="12"/>@<Node id="13"/>ucsu<Node id="17"/>.<Node id="18"/>Colorado<Node id="26"/>.<Node id="27"/>EDU<Node id="30"/> <Node id="31"/>(<Node id="32"/>Frank<Node id="37"/> <Node id="38"/>Crary<Node id="43"/>)<Node id="44"/>
<Node id="45"/>Message-<Node id="53"/>ID<Node id="55"/>:<Node id="56"/> <Node id="57"/>&lt;<Node id="58"/>1993<Node id="62"/>Apr<Node id="65"/>6<Node id="66"/>.<Node id="67"/>035052<Node id="73"/>.<Node id="74"/>18187<Node id="79"/>@<Node id="80"/>ucsu<Node id="84"/>.<Node id="85"/>Colorado<Node id="93"/>.<Node id="94"/>EDU<Node id="97"/>&gt;<Node id="98"/>
<Node id="99"/>Sender<Node id="105"/>:<Node id="106"/> <Node id="107"/>news<Node id="111"/>@<Node id="112"/>ucsu<Node id="116"/>.<Node id="117"/>Colorado<Node id="125"/>.<Node id="126"/>EDU<Node id="129"/> <Node id="130"/>(<Node id="131"/>USENET<Node id="137"/> <Node id="138"/>News<Node id="142"/> <Node id="143"/>System<Node id="149"/>)<Node id="150"/>
<Node id="151"/>Nntp-<Node id="156"/>Posting-<Node id="164"/>Host<Node id="168"/>:<Node id="169"/> <Node id="170"/>ucsu<Node id="174"/>.<Node id="175"/>colorado<Node id="183"/>.<Node id="184"/>edu<Node id="187"/>
<Node id="188"/>Organization<Node id="200"/>:<Node id="201"/> <Node id="202"/>University<Node id="212"/> <Node id="213"/>of<Node id="215"/> <Node id="216"/>Colorado<Node id="224"/>,<Node id="225"/> <Node id="226"/>Boulder<Node id="233"/>
<Node id="234"/>References<Node id="244"/>:<Node id="245"/> <Node id="246"/>&lt;<Node id="247"/>1993<Node id="251"/>Apr<Node id="254"/>3<Node id="255"/>.<Node id="256"/>075441<Node id="262"/>.<Node id="263"/>20755<Node id="268"/>@<Node id="269"/>osuunx<Node id="275"/>.<Node id="276"/>ucc<Node id="279"/>.<Node id="280"/>okstate<Node id="287"/>.<Node id="288"/>edu<Node id="291"/>&gt;<Node id="292"/> <Node id="293"/>&lt;<Node id="294"/>1<Node id="295"/>pqsruINNiae<Node id="306"/>@<Node id="307"/>hp-col<Node id="313"/>.<Node id="314"/>col<Node id="317"/>.<Node id="318"/>hp<Node id="320"/>.<Node id="321"/>com<Node id="324"/>&gt;<Node id="325"/>
<Node id="326"/>Date<Node id="330"/>:<Node id="331"/> <Node id="332"/>Tue<Node id="335"/>,<Node id="336"/> <Node id="337"/>6<Node id="338"/> <Node id="339"/>Apr<Node id="342"/> <Node id="343"/>1993<Node id="347"/> <Node id="348"/>03<Node id="350"/>:<Node id="351"/>50<Node id="353"/>:<Node id="354"/>52<Node id="356"/> <Node id="357"/>GMT<Node id="360"/>
<Node id="361"/>Lines<Node id="366"/>:<Node id="367"/> <Node id="368"/>29<Node id="370"/>
<Node id="371"/>
<Node id="372"/>In<Node id="374"/> <Node id="375"/>article<Node id="382"/> <Node id="383"/>&lt;<Node id="384"/>1<Node id="385"/>pqsruINNiae<Node id="396"/>@<Node id="397"/>hp-col<Node id="403"/>.<Node id="404"/>col<Node id="407"/>.<Node id="408"/>hp<Node id="410"/>.<Node id="411"/>com<Node id="414"/>&gt;<Node id="415"/> <Node id="416"/>dduff<Node id="421"/>@<Node id="422"/>col<Node id="425"/>.<Node id="426"/>hp<Node id="428"/>.<Node id="429"/>com<Node id="432"/> <Node id="433"/>(<Node id="434"/>Dave<Node id="438"/> <Node id="439"/>Duff<Node id="443"/>)<Node id="444"/> <Node id="445"/>writes<Node id="451"/>:<Node id="452"/>
<Node id="453"/>&gt;<Node id="454"/>Does<Node id="458"/> <Node id="459"/>anyone<Node id="465"/> <Node id="466"/>really<Node id="472"/> <Node id="473"/>believe<Node id="480"/> <Node id="481"/>the<Node id="484"/> <Node id="485"/>Swiss<Node id="490"/> <Node id="491"/>have<Node id="495"/> <Node id="496"/>had<Node id="499"/> <Node id="500"/>no<Node id="502"/> <Node id="503"/>war<Node id="506"/> <Node id="507"/>within<Node id="513"/> <Node id="514"/>their<Node id="519"/> <Node id="520"/>borders<Node id="527"/>
<Node id="528"/>&gt;<Node id="529"/>because<Node id="536"/> <Node id="537"/>every<Node id="542"/> <Node id="543"/>adult<Node id="548"/> <Node id="549"/>male<Node id="553"/> <Node id="554"/>owns<Node id="558"/> <Node id="559"/>a<Node id="560"/> <Node id="561"/>rifle<Node id="566"/>?<Node id="567"/> <Node id="568"/>I<Node id="569"/>'m<Node id="571"/> <Node id="572"/>a<Node id="573"/> <Node id="574"/>great<Node id="579"/> <Node id="580"/>admirer<Node id="587"/> <Node id="588"/>of<Node id="590"/> <Node id="591"/>the<Node id="594"/> <Node id="595"/>Swiss<Node id="600"/>,<Node id="601"/> <Node id="602"/>but<Node id="605"/>
<Node id="606"/>&gt;<Node id="607"/>500<Node id="610"/> <Node id="611"/>years<Node id="616"/> <Node id="617"/>of<Node id="619"/> <Node id="620"/>peace<Node id="625"/> <Node id="626"/>on<Node id="628"/> <Node id="629"/>their<Node id="634"/> <Node id="635"/>turf<Node id="639"/> <Node id="640"/>has<Node id="643"/> <Node id="644"/>zilch<Node id="649"/> <Node id="650"/>to<Node id="652"/> <Node id="653"/>do<Node id="655"/> <Node id="656"/>with<Node id="660"/> <Node id="661"/>gun<Node id="664"/> <Node id="665"/>ownership<Node id="674"/>.<Node id="675"/> <Node id="676"/>Can<Node id="679"/> <Node id="680"/>you<Node id="683"/>
<Node id="684"/>&gt;<Node id="685"/>picture<Node id="692"/> <Node id="693"/>Hitler<Node id="699"/>,<Node id="700"/> <Node id="701"/>with<Node id="705"/> <Node id="706"/>Panzers<Node id="713"/> <Node id="714"/>and<Node id="717"/> <Node id="718"/>Focke-<Node id="724"/>Wulfs<Node id="729"/> <Node id="730"/>poised<Node id="736"/> <Node id="737"/>on<Node id="739"/> <Node id="740"/>the<Node id="743"/> <Node id="744"/>border<Node id="750"/>,<Node id="751"/> <Node id="752"/>losing<Node id="758"/>
<Node id="759"/>&gt;<Node id="760"/>sleep<Node id="765"/> <Node id="766"/>over<Node id="770"/> <Node id="771"/>a<Node id="772"/> <Node id="773"/>few<Node id="776"/> <Node id="777"/>thousand<Node id="785"/> <Node id="786"/>expert<Node id="792"/> <Node id="793"/>rifleman<Node id="801"/>?<Node id="802"/> <Node id="803"/>Sure<Node id="807"/>.<Node id="808"/> <Node id="809"/>
<Node id="810"/>
<Node id="811"/>The<Node id="814"/> <Node id="815"/>Swiss<Node id="820"/> <Node id="821"/>population<Node id="831"/> <Node id="832"/>is<Node id="834"/> <Node id="835"/>(<Node id="836"/>and<Node id="839"/> <Node id="840"/>well<Node id="844"/> <Node id="845"/>was<Node id="848"/>)<Node id="849"/> <Node id="850"/>far<Node id="853"/> <Node id="854"/>larger<Node id="860"/> <Node id="861"/>than<Node id="865"/> <Node id="866"/>that<Node id="870"/>.<Node id="871"/> <Node id="872"/>I<Node id="873"/> <Node id="874"/>think<Node id="879"/>
<Node id="880"/>your<Node id="884"/> <Node id="885"/>question<Node id="893"/> <Node id="894"/>should<Node id="900"/> <Node id="901"/>be<Node id="903"/>,<Node id="904"/> <Node id="905"/>"<Node id="906"/>.<Node id="907"/>.<Node id="908"/>.<Node id="909"/>losing<Node id="915"/> <Node id="916"/>sleep<Node id="921"/> <Node id="922"/>over<Node id="926"/> <Node id="927"/>a<Node id="928"/> <Node id="929"/>million<Node id="936"/> <Node id="937"/>expert<Node id="943"/>
<Node id="944"/>riflemen<Node id="952"/>?<Node id="953"/>"<Node id="954"/> <Node id="955"/>Certainly<Node id="964"/> <Node id="965"/>he<Node id="967"/> <Node id="968"/>could<Node id="973"/> <Node id="974"/>have<Node id="978"/> <Node id="979"/>conquered<Node id="988"/> <Node id="989"/>Switzerland<Node id="1000"/>,<Node id="1001"/> <Node id="1002"/>but<Node id="1005"/>
<Node id="1006"/>a<Node id="1007"/> <Node id="1008"/>million<Node id="1015"/> <Node id="1016"/>armed<Node id="1021"/> <Node id="1022"/>militiamen<Node id="1032"/> <Node id="1033"/>(<Node id="1034"/>especially<Node id="1044"/> <Node id="1045"/>in<Node id="1047"/> <Node id="1048"/>a<Node id="1049"/> <Node id="1050"/>mountainous<Node id="1061"/> <Node id="1062"/>area<Node id="1066"/>,<Node id="1067"/> <Node id="1068"/>
<Node id="1069"/>where<Node id="1074"/> <Node id="1075"/>tanks<Node id="1080"/>'<Node id="1081"/> <Node id="1082"/>effectiveness<Node id="1095"/> <Node id="1096"/>is<Node id="1098"/> <Node id="1099"/>limited<Node id="1106"/>)<Node id="1107"/> <Node id="1108"/>would<Node id="1113"/> <Node id="1114"/>have<Node id="1118"/> <Node id="1119"/>made<Node id="1123"/> <Node id="1124"/>it<Node id="1126"/> <Node id="1127"/>a<Node id="1128"/>
<Node id="1129"/>real<Node id="1133"/> <Node id="1134"/>pain<Node id="1138"/>.<Node id="1139"/> <Node id="1140"/>The<Node id="1143"/> <Node id="1144"/>question<Node id="1152"/> <Node id="1153"/>a<Node id="1154"/> <Node id="1155"/>conqueror<Node id="1164"/> <Node id="1165"/>would<Node id="1170"/> <Node id="1171"/>ask<Node id="1174"/>,<Node id="1175"/> <Node id="1176"/>is<Node id="1178"/> <Node id="1179"/>"<Node id="1180"/>is<Node id="1182"/> <Node id="1183"/>it<Node id="1185"/> <Node id="1186"/>worth<Node id="1191"/> <Node id="1192"/>
<Node id="1193"/>the<Node id="1196"/> <Node id="1197"/>trouble<Node id="1204"/>?<Node id="1205"/>"<Node id="1206"/> <Node id="1207"/>The<Node id="1210"/> <Node id="1211"/>more<Node id="1215"/> <Node id="1216"/>difficult<Node id="1225"/> <Node id="1226"/>an<Node id="1228"/> <Node id="1229"/>invasion<Node id="1237"/> <Node id="1238"/>is<Node id="1240"/>,<Node id="1241"/> <Node id="1242"/>the<Node id="1245"/> <Node id="1246"/>more<Node id="1250"/> <Node id="1251"/>likely<Node id="1257"/>
<Node id="1258"/>the<Node id="1261"/> <Node id="1262"/>answer<Node id="1268"/> <Node id="1269"/>would<Node id="1274"/> <Node id="1275"/>be<Node id="1277"/> <Node id="1278"/>"<Node id="1279"/>no<Node id="1281"/>.<Node id="1282"/>"<Node id="1283"/> <Node id="1284"/>Certainly<Node id="1293"/> <Node id="1294"/>a<Node id="1295"/> <Node id="1296"/>million<Node id="1303"/> <Node id="1304"/>riflemen<Node id="1312"/> <Node id="1313"/>(<Node id="1314"/>as<Node id="1316"/>
<Node id="1317"/>opposed<Node id="1324"/> <Node id="1325"/>to<Node id="1327"/> <Node id="1328"/>a<Node id="1329"/> <Node id="1330"/>professional<Node id="1342"/> <Node id="1343"/>army<Node id="1347"/> <Node id="1348"/>of<Node id="1350"/> <Node id="1351"/>only<Node id="1355"/> <Node id="1356"/>ten<Node id="1359"/> <Node id="1360"/>or<Node id="1362"/> <Node id="1363"/>twenty<Node id="1369"/> <Node id="1370"/>thousand<Node id="1378"/>,<Node id="1379"/> <Node id="1380"/>the<Node id="1383"/>
<Node id="1384"/>best<Node id="1388"/> <Node id="1389"/>a<Node id="1390"/> <Node id="1391"/>country<Node id="1398"/> <Node id="1399"/>the<Node id="1402"/> <Node id="1403"/>size<Node id="1407"/> <Node id="1408"/>of<Node id="1410"/> <Node id="1411"/>Switzerland<Node id="1422"/> <Node id="1423"/>could<Node id="1428"/> <Node id="1429"/>support<Node id="1436"/>)<Node id="1437"/>,<Node id="1438"/> <Node id="1439"/>makes<Node id="1444"/>
<Node id="1445"/>invasions<Node id="1454"/> <Node id="1455"/>more<Node id="1459"/> <Node id="1460"/>difficult<Node id="1469"/>.<Node id="1470"/>
<Node id="1471"/>
<Node id="1472"/>&gt;<Node id="1473"/>Hitler<Node id="1479"/> <Node id="1480"/>stayed<Node id="1486"/> <Node id="1487"/>out<Node id="1490"/> <Node id="1491"/>of<Node id="1493"/> <Node id="1494"/>Switzerland<Node id="1505"/> <Node id="1506"/>because<Node id="1513"/> <Node id="1514"/>the<Node id="1517"/> <Node id="1518"/>Swiss<Node id="1523"/> <Node id="1524"/>run<Node id="1527"/> <Node id="1528"/>the<Node id="1531"/> <Node id="1532"/>money<Node id="1537"/> <Node id="1538"/>in<Node id="1540"/> <Node id="1541"/>this<Node id="1545"/>
<Node id="1546"/>&gt;<Node id="1547"/>world<Node id="1552"/>.<Node id="1553"/>
<Node id="1554"/>
<Node id="1555"/>Really<Node id="1561"/>?<Node id="1562"/> <Node id="1563"/>In<Node id="1565"/> <Node id="1566"/>1939<Node id="1570"/>?<Node id="1571"/> <Node id="1572"/>I<Node id="1573"/>'m<Node id="1575"/> <Node id="1576"/>not<Node id="1579"/> <Node id="1580"/>even<Node id="1584"/> <Node id="1585"/>sure<Node id="1589"/> <Node id="1590"/>you<Node id="1593"/> <Node id="1594"/>could<Node id="1599"/> <Node id="1600"/>prove<Node id="1605"/> <Node id="1606"/>that<Node id="1610"/> <Node id="1611"/>today<Node id="1616"/> <Node id="1617"/>(<Node id="1618"/>despite<Node id="1625"/>
<Node id="1626"/>the<Node id="1629"/> <Node id="1630"/>steriotype<Node id="1640"/>.<Node id="1641"/>)<Node id="1642"/> <Node id="1643"/>Certainly<Node id="1652"/> <Node id="1653"/>the<Node id="1656"/> <Node id="1657"/>Swiss<Node id="1662"/> <Node id="1663"/>bankers<Node id="1670"/> <Node id="1671"/>were<Node id="1675"/> <Node id="1676"/>not<Node id="1679"/> <Node id="1680"/>essential<Node id="1689"/>
<Node id="1690"/>to<Node id="1692"/> <Node id="1693"/>the<Node id="1696"/> <Node id="1697"/>German<Node id="1703"/> <Node id="1704"/>war-time<Node id="1712"/> <Node id="1713"/>economy<Node id="1720"/>.<Node id="1721"/>
<Node id="1722"/>
<Node id="1723"/> <Node id="1724"/> <Node id="1725"/> <Node id="1726"/> <Node id="1727"/> <Node id="1728"/> <Node id="1729"/> <Node id="1730"/> <Node id="1731"/> <Node id="1732"/> <Node id="1733"/> <Node id="1734"/> <Node id="1735"/> <Node id="1736"/> <Node id="1737"/> <Node id="1738"/> <Node id="1739"/> <Node id="1740"/> <Node id="1741"/> <Node id="1742"/> <Node id="1743"/> <Node id="1744"/> <Node id="1745"/> <Node id="1746"/> <Node id="1747"/> <Node id="1748"/> <Node id="1749"/> <Node id="1750"/> <Node id="1751"/> <Node id="1752"/> <Node id="1753"/> <Node id="1754"/> <Node id="1755"/> <Node id="1756"/> <Node id="1757"/> <Node id="1758"/> <Node id="1759"/> <Node id="1760"/> <Node id="1761"/> <Node id="1762"/> <Node id="1763"/> <Node id="1764"/> <Node id="1765"/> <Node id="1766"/>Frank<Node id="1771"/> <Node id="1772"/>Crary<Node id="1777"/>
<Node id="1778"/> <Node id="1779"/> <Node id="1780"/> <Node id="1781"/> <Node id="1782"/> <Node id="1783"/> <Node id="1784"/> <Node id="1785"/> <Node id="1786"/> <Node id="1787"/> <Node id="1788"/> <Node id="1789"/> <Node id="1790"/> <Node id="1791"/> <Node id="1792"/> <Node id="1793"/> <Node id="1794"/> <Node id="1795"/> <Node id="1796"/> <Node id="1797"/> <Node id="1798"/> <Node id="1799"/> <Node id="1800"/> <Node id="1801"/> <Node id="1802"/> <Node id="1803"/> <Node id="1804"/> <Node id="1805"/> <Node id="1806"/> <Node id="1807"/> <Node id="1808"/> <Node id="1809"/> <Node id="1810"/> <Node id="1811"/> <Node id="1812"/> <Node id="1813"/> <Node id="1814"/> <Node id="1815"/> <Node id="1816"/> <Node id="1817"/> <Node id="1818"/> <Node id="1819"/> <Node id="1820"/> <Node id="1821"/>CU<Node id="1823"/> <Node id="1824"/>Boulder<Node id="1831"/>
<Node id="1832"/>
<Node id="1833"/></TextWithNodes>
<!-- The default annotation set -->

<AnnotationSet>
<Annotation EndNode="1833" StartNode="0" Type="Mention" Id="9999999">
<Feature>
<Name classname="java.lang.String">Class</Name>
<Value classname="java.lang.String">0</Value>
</Feature>
</Annotation>

<Annotation Id="3" Type="Token" StartNode="6" EndNode="12">
<Feature>
  <Name className="java.lang.String">string</Name>
  <Value className="java.lang.String">fcrary</Value>
</Feature>
</Annotation>
<Annotation Id="7" Type="Token" StartNode="18" EndNode="26">
<Feature>
  <Name className="java.lang.String">string</Name>
  <Value className="java.lang.String">Colorado</Value>
</Feature>
</Annotation>
<Annotation Id="17" Type="Token" StartNode="45" EndNode="53">
<Feature>
  <Name className="java.lang.String">string</Name>
  <Value className="java.lang.String">Message-</Value>
</Feature>
</Annotation>
<Annotation Id="26" Type="Token" StartNode="67" EndNode="73">
</Annotation>
<Annotation Id="32" Type="Token" StartNode="85" EndNode="93">
<Feature>
  <Name className="java.lang.String">string</Name>
  <Value className="java.lang.String">Colorado</Value>
</Feature>
</Annotation>
<Annotation Id="37" Type="Token" StartNode="99" EndNode="105">
<Feature>
  <Name className="java.lang.String">string</Name>
  <Value className="java.lang.String">Sender</Value>
</Feature>
</Annotation>
<Annotation Id="44" Type="Token" StartNode="117" EndNode="125">
<Feature>
  <Name className="java.lang.String">string</Name>
  <Value className="java.lang.String">Colorado</Value>
</Feature>
</Annotation>
<Annotation Id="49" Type="Token" StartNode="131" EndNode="137">
<Feature>
  <Name className="java.lang.String">string</Name>
  <Value className="java.lang.String">USENET</Value>
</Feature>
</Annotation>
<Annotation Id="53" Type="Token" StartNode="143" EndNode="149">
<Feature>
  <Name className="java.lang.String">string</Name>
  <Value className="java.lang.String">System</Value>
</Feature>
</Annotation>
<Annotation Id="57" Type="Token" StartNode="156" EndNode="164">
<Feature>
  <Name className="java.lang.String">string</Name>
  <Value className="java.lang.String">Posting-</Value>
</Feature>
</Annotation>
<Annotation Id="63" Type="Token" StartNode="175" EndNode="183">
<Feature>
  <Name className="java.lang.String">string</Name>
  <Value className="java.lang.String">colorado</Value>
</Feature>
</Annotation>
<Annotation Id="70" Type="Token" StartNode="202" EndNode="212">
<Feature>
  <Name className="java.lang.String">string</Name>
  <Value className="java.lang.String">University</Value>
</Feature>
</Annotation>
<Annotation Id="67" Type="Token" StartNode="188" EndNode="200">
<Feature>
  <Name className="java.lang.String">string</Name>
  <Value className="java.lang.String">Organization</Value>
</Feature>
</Annotation>
<Annotation Id="77" Type="Token" StartNode="226" EndNode="233">
<Feature>
  <Name className="java.lang.String">string</Name>
  <Value className="java.lang.String">Boulder</Value>
</Feature>
</Annotation>
<Annotation Id="79" Type="Token" StartNode="234" EndNode="244">
<Feature>
  <Name className="java.lang.String">string</Name>
  <Value className="java.lang.String">References</Value>
</Feature>
</Annotation>
<Annotation Id="74" Type="Token" StartNode="216" EndNode="224">
<Feature>
  <Name className="java.lang.String">string</Name>
  <Value className="java.lang.String">Colorado</Value>
</Feature>
</Annotation>
<Annotation Id="87" Type="Token" StartNode="256" EndNode="262">
</Annotation>
<Annotation Id="95" Type="Token" StartNode="280" EndNode="287">
<Feature>
  <Name className="java.lang.String">string</Name>
  <Value className="java.lang.String">okstate</Value>
</Feature>
</Annotation>
<Annotation Id="91" Type="Token" StartNode="269" EndNode="275">
<Feature>
  <Name className="java.lang.String">string</Name>
  <Value className="java.lang.String">osuunx</Value>
</Feature>
</Annotation>
<Annotation Id="102" Type="Token" StartNode="295" EndNode="306">
<Feature>
  <Name className="java.lang.String">string</Name>
  <Value className="java.lang.String">pqsruINNiae</Value>
</Feature>
</Annotation>
<Annotation Id="104" Type="Token" StartNode="307" EndNode="313">
<Feature>
  <Name className="java.lang.String">string</Name>
  <Value className="java.lang.String">hp-col</Value>
</Feature>
</Annotation>
<Annotation Id="141" Type="Token" StartNode="375" EndNode="382">
<Feature>
  <Name className="java.lang.String">string</Name>
  <Value className="java.lang.String">article</Value>
</Feature>
</Annotation>
<Annotation Id="145" Type="Token" StartNode="385" EndNode="396">
<Feature>
  <Name className="java.lang.String">string</Name>
  <Value className="java.lang.String">pqsruINNiae</Value>
</Feature>
</Annotation>
<Annotation Id="147" Type="Token" StartNode="397" EndNode="403">
<Feature>
  <Name className="java.lang.String">string</Name>
  <Value className="java.lang.String">hp-col</Value>
</Feature>
</Annotation>
<Annotation Id="170" Type="Token" StartNode="445" EndNode="451">
<Feature>
  <Name className="java.lang.String">string</Name>
  <Value className="java.lang.String">writes</Value>
</Feature>
</Annotation>
<Annotation Id="178" Type="Token" StartNode="466" EndNode="472">
<Feature>
  <Name className="java.lang.String">string</Name>
  <Value className="java.lang.String">really</Value>
</Feature>
</Annotation>
<Annotation Id="176" Type="Token" StartNode="459" EndNode="465">
<Feature>
  <Name className="java.lang.String">string</Name>
  <Value className="java.lang.String">anyone</Value>
</Feature>
</Annotation>
<Annotation Id="180" Type="Token" StartNode="473" EndNode="480">
<Feature>
  <Name className="java.lang.String">string</Name>
  <Value className="java.lang.String">believe</Value>
</Feature>
</Annotation>
<Annotation Id="201" Type="Token" StartNode="529" EndNode="536">
<Feature>
  <Name className="java.lang.String">string</Name>
  <Value className="java.lang.String">because</Value>
</Feature>
</Annotation>
<Annotation Id="198" Type="Token" StartNode="520" EndNode="527">
<Feature>
  <Name className="java.lang.String">string</Name>
  <Value className="java.lang.String">borders</Value>
</Feature>
</Annotation>
<Annotation Id="194" Type="Token" StartNode="507" EndNode="513">
<Feature>
  <Name className="java.lang.String">string</Name>
  <Value className="java.lang.String">within</Value>
</Feature>
</Annotation>
<Annotation Id="224" Type="Token" StartNode="580" EndNode="587">
<Feature>
  <Name className="java.lang.String">string</Name>
  <Value className="java.lang.String">admirer</Value>
</Feature>
</Annotation>
<Annotation Id="272" Type="Token" StartNode="693" EndNode="699">
<Feature>
  <Name className="java.lang.String">string</Name>
  <Value className="java.lang.String">Hitler</Value>
</Feature>
</Annotation>
<Annotation Id="277" Type="Token" StartNode="706" EndNode="713">
<Feature>
  <Name className="java.lang.String">string</Name>
  <Value className="java.lang.String">Panzers</Value>
</Feature>
</Annotation>
<Annotation Id="281" Type="Token" StartNode="718" EndNode="724">
<Feature>
  <Name className="java.lang.String">string</Name>
  <Value className="java.lang.String">Focke-</Value>
</Feature>
</Annotation>
<Annotation Id="284" Type="Token" StartNode="730" EndNode="736">
<Feature>
  <Name className="java.lang.String">string</Name>
  <Value className="java.lang.String">poised</Value>
</Feature>
</Annotation>
<Annotation Id="262" Type="Token" StartNode="665" EndNode="674">
<Feature>
  <Name className="java.lang.String">string</Name>
  <Value className="java.lang.String">ownership</Value>
</Feature>
</Annotation>
<Annotation Id="270" Type="Token" StartNode="685" EndNode="692">
<Feature>
  <Name className="java.lang.String">string</Name>
  <Value className="java.lang.String">picture</Value>
</Feature>
</Annotation>
<Annotation Id="304" Type="Token" StartNode="777" EndNode="785">
<Feature>
  <Name className="java.lang.String">string</Name>
  <Value className="java.lang.String">thousand</Value>
</Feature>
</Annotation>
<Annotation Id="306" Type="Token" StartNode="786" EndNode="792">
<Feature>
  <Name className="java.lang.String">string</Name>
  <Value className="java.lang.String">expert</Value>
</Feature>
</Annotation>
<Annotation Id="308" Type="Token" StartNode="793" EndNode="801">
<Feature>
  <Name className="java.lang.String">string</Name>
  <Value className="java.lang.String">rifleman</Value>
</Feature>
</Annotation>
<Annotation Id="290" Type="Token" StartNode="744" EndNode="750">
<Feature>
  <Name className="java.lang.String">string</Name>
  <Value className="java.lang.String">border</Value>
</Feature>
</Annotation>
<Annotation Id="293" Type="Token" StartNode="752" EndNode="758">
<Feature>
  <Name className="java.lang.String">string</Name>
  <Value className="java.lang.String">losing</Value>
</Feature>
</Annotation>
<Annotation Id="349" Type="Token" StartNode="894" EndNode="900">
<Feature>
  <Name className="java.lang.String">string</Name>
  <Value className="java.lang.String">should</Value>
</Feature>
</Annotation>
<Annotation Id="347" Type="Token" StartNode="885" EndNode="893">
<Feature>
  <Name className="java.lang.String">string</Name>
  <Value className="java.lang.String">question</Value>
</Feature>
</Annotation>
<Annotation Id="320" Type="Token" StartNode="821" EndNode="831">
<Feature>
  <Name className="java.lang.String">string</Name>
  <Value className="java.lang.String">population</Value>
</Feature>
</Annotation>
<Annotation Id="334" Type="Token" StartNode="854" EndNode="860">
<Feature>
  <Name className="java.lang.String">string</Name>
  <Value className="java.lang.String">larger</Value>
</Feature>
</Annotation>
<Annotation Id="374" Type="Token" StartNode="955" EndNode="964">
<Feature>
  <Name className="java.lang.String">string</Name>
  <Value className="java.lang.String">Certainly</Value>
</Feature>
</Annotation>
<Annotation Id="368" Type="Token" StartNode="937" EndNode="943">
<Feature>
  <Name className="java.lang.String">string</Name>
  <Value className="java.lang.String">expert</Value>
</Feature>
</Annotation>
<Annotation Id="370" Type="Token" StartNode="944" EndNode="952">
<Feature>
  <Name className="java.lang.String">string</Name>
  <Value className="java.lang.String">riflemen</Value>
</Feature>
</Annotation>
<Annotation Id="382" Type="Token" StartNode="979" EndNode="988">
<Feature>
  <Name className="java.lang.String">string</Name>
  <Value className="java.lang.String">conquered</Value>
</Feature>
</Annotation>
<Annotation Id="358" Type="Token" StartNode="909" EndNode="915">
<Feature>
  <Name className="java.lang.String">string</Name>
  <Value className="java.lang.String">losing</Value>
</Feature>
</Annotation>
<Annotation Id="366" Type="Token" StartNode="929" EndNode="936">
<Feature>
  <Name className="java.lang.String">string</Name>
  <Value className="java.lang.String">million</Value>
</Feature>
</Annotation>
<Annotation Id="415" Type="Token" StartNode="1082" EndNode="1095">
<Feature>
  <Name className="java.lang.String">string</Name>
  <Value className="java.lang.String">effectiveness</Value>
</Feature>
</Annotation>
<Annotation Id="404" Type="Token" StartNode="1050" EndNode="1061">
<Feature>
  <Name className="java.lang.String">string</Name>
  <Value className="java.lang.String">mountainous</Value>
</Feature>
</Annotation>
<Annotation Id="395" Type="Token" StartNode="1022" EndNode="1032">
<Feature>
  <Name className="java.lang.String">string</Name>
  <Value className="java.lang.String">militiamen</Value>
</Feature>
</Annotation>
<Annotation Id="398" Type="Token" StartNode="1034" EndNode="1044">
<Feature>
  <Name className="java.lang.String">string</Name>
  <Value className="java.lang.String">especially</Value>
</Feature>
</Annotation>
<Annotation Id="384" Type="Token" StartNode="989" EndNode="1000">
<Feature>
  <Name className="java.lang.String">string</Name>
  <Value className="java.lang.String">Switzerland</Value>
</Feature>
</Annotation>
<Annotation Id="391" Type="Token" StartNode="1008" EndNode="1015">
<Feature>
  <Name className="java.lang.String">string</Name>
  <Value className="java.lang.String">million</Value>
</Feature>
</Annotation>
<Annotation Id="443" Type="Token" StartNode="1155" EndNode="1164">
<Feature>
  <Name className="java.lang.String">string</Name>
  <Value className="java.lang.String">conqueror</Value>
</Feature>
</Annotation>
<Annotation Id="439" Type="Token" StartNode="1144" EndNode="1152">
<Feature>
  <Name className="java.lang.String">string</Name>
  <Value className="java.lang.String">question</Value>
</Feature>
</Annotation>
<Annotation Id="419" Type="Token" StartNode="1099" EndNode="1106">
<Feature>
  <Name className="java.lang.String">string</Name>
  <Value className="java.lang.String">limited</Value>
</Feature>
</Annotation>
<Annotation Id="474" Type="Token" StartNode="1229" EndNode="1237">
<Feature>
  <Name className="java.lang.String">string</Name>
  <Value className="java.lang.String">invasion</Value>
</Feature>
</Annotation>
<Annotation Id="470" Type="Token" StartNode="1216" EndNode="1225">
<Feature>
  <Name className="java.lang.String">string</Name>
  <Value className="java.lang.String">difficult</Value>
</Feature>
</Annotation>
<Annotation Id="462" Type="Token" StartNode="1197" EndNode="1204">
<Feature>
  <Name className="java.lang.String">string</Name>
  <Value className="java.lang.String">trouble</Value>
</Feature>
</Annotation>
<Annotation Id="509" Type="Token" StartNode="1317" EndNode="1324">
<Feature>
  <Name className="java.lang.String">string</Name>
  <Value className="java.lang.String">opposed</Value>
</Feature>
</Annotation>
<Annotation Id="504" Type="Token" StartNode="1304" EndNode="1312">
<Feature>
  <Name className="java.lang.String">string</Name>
  <Value className="java.lang.String">riflemen</Value>
</Feature>
</Annotation>
<Annotation Id="502" Type="Token" StartNode="1296" EndNode="1303">
<Feature>
  <Name className="java.lang.String">string</Name>
  <Value className="java.lang.String">million</Value>
</Feature>
</Annotation>
<Annotation Id="498" Type="Token" StartNode="1284" EndNode="1293">
<Feature>
  <Name className="java.lang.String">string</Name>
  <Value className="java.lang.String">Certainly</Value>
</Feature>
</Annotation>
<Annotation Id="487" Type="Token" StartNode="1262" EndNode="1268">
<Feature>
  <Name className="java.lang.String">string</Name>
  <Value className="java.lang.String">answer</Value>
</Feature>
</Annotation>
<Annotation Id="483" Type="Token" StartNode="1251" EndNode="1257">
<Feature>
  <Name className="java.lang.String">string</Name>
  <Value className="java.lang.String">likely</Value>
</Feature>
</Annotation>
<Annotation Id="550" Type="Token" StartNode="1429" EndNode="1436">
<Feature>
  <Name className="java.lang.String">string</Name>
  <Value className="java.lang.String">support</Value>
</Feature>
</Annotation>
<Annotation Id="546" Type="Token" StartNode="1411" EndNode="1422">
<Feature>
  <Name className="java.lang.String">string</Name>
  <Value className="java.lang.String">Switzerland</Value>
</Feature>
</Annotation>
<Annotation Id="556" Type="Token" StartNode="1445" EndNode="1454">
<Feature>
  <Name className="java.lang.String">string</Name>
  <Value className="java.lang.String">invasions</Value>
</Feature>
</Annotation>
<Annotation Id="567" Type="Token" StartNode="1480" EndNode="1486">
<Feature>
  <Name className="java.lang.String">string</Name>
  <Value className="java.lang.String">stayed</Value>
</Feature>
</Annotation>
<Annotation Id="565" Type="Token" StartNode="1473" EndNode="1479">
<Feature>
  <Name className="java.lang.String">string</Name>
  <Value className="java.lang.String">Hitler</Value>
</Feature>
</Annotation>
<Annotation Id="560" Type="Token" StartNode="1460" EndNode="1469">
<Feature>
  <Name className="java.lang.String">string</Name>
  <Value className="java.lang.String">difficult</Value>
</Feature>
</Annotation>
<Annotation Id="575" Type="Token" StartNode="1506" EndNode="1513">
<Feature>
  <Name className="java.lang.String">string</Name>
  <Value className="java.lang.String">because</Value>
</Feature>
</Annotation>
<Annotation Id="573" Type="Token" StartNode="1494" EndNode="1505">
<Feature>
  <Name className="java.lang.String">string</Name>
  <Value className="java.lang.String">Switzerland</Value>
</Feature>
</Annotation>
<Annotation Id="515" Type="Token" StartNode="1330" EndNode="1342">
<Feature>
  <Name className="java.lang.String">string</Name>
  <Value className="java.lang.String">professional</Value>
</Feature>
</Annotation>
<Annotation Id="527" Type="Token" StartNode="1363" EndNode="1369">
<Feature>
  <Name className="java.lang.String">string</Name>
  <Value className="java.lang.String">twenty</Value>
</Feature>
</Annotation>
<Annotation Id="529" Type="Token" StartNode="1370" EndNode="1378">
<Feature>
  <Name className="java.lang.String">string</Name>
  <Value className="java.lang.String">thousand</Value>
</Feature>
</Annotation>
<Annotation Id="538" Type="Token" StartNode="1391" EndNode="1398">
<Feature>
  <Name className="java.lang.String">string</Name>
  <Value className="java.lang.String">country</Value>
</Feature>
</Annotation>
<Annotation Id="625" Type="Token" StartNode="1618" EndNode="1625">
<Feature>
  <Name className="java.lang.String">string</Name>
  <Value className="java.lang.String">despite</Value>
</Feature>
</Annotation>
<Annotation Id="629" Type="Token" StartNode="1630" EndNode="1640">
<Feature>
  <Name className="java.lang.String">string</Name>
  <Value className="java.lang.String">steriotype</Value>
</Feature>
</Annotation>
<Annotation Id="633" Type="Token" StartNode="1643" EndNode="1652">
<Feature>
  <Name className="java.lang.String">string</Name>
  <Value className="java.lang.String">Certainly</Value>
</Feature>
</Annotation>
<Annotation Id="639" Type="Token" StartNode="1663" EndNode="1670">
<Feature>
  <Name className="java.lang.String">string</Name>
  <Value className="java.lang.String">bankers</Value>
</Feature>
</Annotation>
<Annotation Id="596" Type="Token" StartNode="1555" EndNode="1561">
<Feature>
  <Name className="java.lang.String">string</Name>
  <Value className="java.lang.String">Really</Value>
</Feature>
</Annotation>
<Annotation Id="653" Type="Token" StartNode="1704" EndNode="1712">
<Feature>
  <Name className="java.lang.String">string</Name>
  <Value className="java.lang.String">war-time</Value>
</Feature>
</Annotation>
<Annotation Id="655" Type="Token" StartNode="1713" EndNode="1720">
<Feature>
  <Name className="java.lang.String">string</Name>
  <Value className="java.lang.String">economy</Value>
</Feature>
</Annotation>
<Annotation Id="651" Type="Token" StartNode="1697" EndNode="1703">
<Feature>
  <Name className="java.lang.String">string</Name>
  <Value className="java.lang.String">German</Value>
</Feature>
</Annotation>
<Annotation Id="645" Type="Token" StartNode="1680" EndNode="1689">
<Feature>
  <Name className="java.lang.String">string</Name>
  <Value className="java.lang.String">essential</Value>
</Feature>
</Annotation>
<Annotation Id="751" Type="Token" StartNode="1824" EndNode="1831">
<Feature>
  <Name className="java.lang.String">string</Name>
  <Value className="java.lang.String">Boulder</Value>
</Feature>
</Annotation>
</AnnotationSet>
<AnnotationSet Name="Original markups"> </AnnotationSet>
</GateDocument>